dashlang/__init__.py
dashlang/components.py
dashlang/exceptions.py
dashlang/grammars.py
dashlang/transforms.py
dashlang/visitor.py
dashlang-0.0.1.dist-info/LICENSE
dashlang-0.0.1.dist-info/METADATA
dashlang-0.0.1.dist-info/WHEEL
dashlang-0.0.1.dist-info/top_level.txt
dashlang-0.0.1.dist-info/RECORD
