Metadata-Version: 2.1
Name: dashlang
Version: 0.0.1
Summary: Experimental markup language for creating rich dashboards using Dash
Home-page: https://gitlab.com/runemaster/dashlang
Author: Pedro Dias
Author-email: pedrodias.miguel@gmail.com
Maintainer: Pedro Dias
Maintainer-email: pedrodias.miguel@gmail.com
License: Unlicense
Platform: UNKNOWN
Classifier: Development Status :: 3 - Alpha
Classifier: Framework :: Dash
Classifier: Intended Audience :: Developers
Classifier: License :: OSI Approved :: The Unlicense (Unlicense)
Classifier: Operating System :: OS Independent
Classifier: Programming Language :: Python
Classifier: Programming Language :: Python :: 3 :: Only
Classifier: Topic :: Software Development :: Libraries
Requires-Python: >=3.7
License-File: LICENSE
Requires-Dist: dash (>1.20.0)
Requires-Dist: parsimonious (==0.8.1)
